royalnet/__init__.py
royalnet/engineer/README.md
royalnet/engineer/__init__.py
royalnet/engineer/bullet/__init__.py
royalnet/engineer/bullet/casing.py
royalnet/engineer/bullet/contents/__init__.py
royalnet/engineer/bullet/contents/_base.py
royalnet/engineer/bullet/contents/_imports.py
royalnet/engineer/bullet/contents/button.py
royalnet/engineer/bullet/contents/button_reaction.py
royalnet/engineer/bullet/contents/channel.py
royalnet/engineer/bullet/contents/message.py
royalnet/engineer/bullet/contents/user.py
royalnet/engineer/bullet/exc.py
royalnet/engineer/bullet/projectiles/__init__.py
royalnet/engineer/bullet/projectiles/_base.py
royalnet/engineer/bullet/projectiles/_imports.py
royalnet/engineer/bullet/projectiles/message.py
royalnet/engineer/bullet/projectiles/reaction.py
royalnet/engineer/bullet/projectiles/user.py
royalnet/engineer/conversation.py
royalnet/engineer/discard.py
royalnet/engineer/dispenser.py
royalnet/engineer/exc.py
royalnet/engineer/pda/__init__.py
royalnet/engineer/pda/base.py
royalnet/engineer/pda/implementations/__init__.py
royalnet/engineer/pda/implementations/base.py
royalnet/engineer/router.py
royalnet/engineer/sentry.py
royalnet/engineer/wrench.py
royalnet/exc.py
royalnet/royaltyping.py
royalnet/validation.py
royalnet-6.7.1.dist-info/entry_points.txt
royalnet-6.7.1.dist-info/LICENSE.txt
royalnet-6.7.1.dist-info/WHEEL
royalnet-6.7.1.dist-info/METADATA
royalnet-6.7.1.dist-info/RECORD
